odoo8_addon_crm_rma_prodlot_invoice-8.0.1.0.0.99.dev28-py3.8-nspkg.pth
odoo_addons/crm_rma_prodlot_invoice/README.rst
odoo_addons/crm_rma_prodlot_invoice/__init__.py
odoo_addons/crm_rma_prodlot_invoice/__openerp__.py
odoo_addons/crm_rma_prodlot_invoice/i18n/ca.po
odoo_addons/crm_rma_prodlot_invoice/i18n/crm_rma_prodlot_invoice.pot
odoo_addons/crm_rma_prodlot_invoice/i18n/de.po
odoo_addons/crm_rma_prodlot_invoice/i18n/es.po
odoo_addons/crm_rma_prodlot_invoice/i18n/es_AR.po
odoo_addons/crm_rma_prodlot_invoice/i18n/es_ES.po
odoo_addons/crm_rma_prodlot_invoice/i18n/es_MX.po
odoo_addons/crm_rma_prodlot_invoice/i18n/es_PA.po
odoo_addons/crm_rma_prodlot_invoice/i18n/es_VE.po
odoo_addons/crm_rma_prodlot_invoice/i18n/fi.po
odoo_addons/crm_rma_prodlot_invoice/i18n/fr.po
odoo_addons/crm_rma_prodlot_invoice/i18n/hr.po
odoo_addons/crm_rma_prodlot_invoice/i18n/hu.po
odoo_addons/crm_rma_prodlot_invoice/i18n/it.po
odoo_addons/crm_rma_prodlot_invoice/i18n/nl.po
odoo_addons/crm_rma_prodlot_invoice/i18n/nl_NL.po
odoo_addons/crm_rma_prodlot_invoice/i18n/pt_BR.po
odoo_addons/crm_rma_prodlot_invoice/i18n/ro.po
odoo_addons/crm_rma_prodlot_invoice/i18n/sk.po
odoo_addons/crm_rma_prodlot_invoice/i18n/sl.po
odoo_addons/crm_rma_prodlot_invoice/i18n/tr.po
odoo_addons/crm_rma_prodlot_invoice/i18n/tr_TR.po
odoo_addons/crm_rma_prodlot_invoice/i18n/zh_CN.po
odoo_addons/crm_rma_prodlot_invoice/models/__init__.py
odoo_addons/crm_rma_prodlot_invoice/models/sale_order.py
odoo_addons/crm_rma_prodlot_invoice/models/sale_order_line.py
odoo_addons/crm_rma_prodlot_invoice/models/stock_picking.py
odoo_addons/crm_rma_prodlot_invoice/models/stock_production_lot.py
odoo_addons/crm_rma_prodlot_invoice/models/stock_transfer_details.py
odoo_addons/crm_rma_prodlot_invoice/static/description/icon.png
odoo_addons/crm_rma_prodlot_invoice/tests/__init__.py
odoo_addons/crm_rma_prodlot_invoice/tests/test_crm_rma_prodlot_invoice.py
odoo_addons/crm_rma_prodlot_invoice/views/stock_production_lot.xml
odoo8_addon_crm_rma_prodlot_invoice-8.0.1.0.0.99.dev28.dist-info/METADATA
odoo8_addon_crm_rma_prodlot_invoice-8.0.1.0.0.99.dev28.dist-info/WHEEL
odoo8_addon_crm_rma_prodlot_invoice-8.0.1.0.0.99.dev28.dist-info/namespace_packages.txt
odoo8_addon_crm_rma_prodlot_invoice-8.0.1.0.0.99.dev28.dist-info/top_level.txt
odoo8_addon_crm_rma_prodlot_invoice-8.0.1.0.0.99.dev28.dist-info/RECORD
